thevenin/__init__.py
thevenin/_basemodel.py
thevenin/_experiment.py
thevenin/_prediction.py
thevenin/_simulation.py
thevenin/_solutions.py
thevenin/loadfns/__init__.py
thevenin/loadfns/_ramps.py
thevenin/loadfns/_steps.py
thevenin/plotutils/__init__.py
thevenin/plotutils/_colors.py
thevenin/solvers/__init__.py
thevenin/solvers/_cvode.py
thevenin/solvers/_ida.py
thevenin/templates/params.yaml
thevenin-0.2.1.dist-info/licenses/LICENSE
thevenin-0.2.1.dist-info/METADATA
thevenin-0.2.1.dist-info/WHEEL
thevenin-0.2.1.dist-info/top_level.txt
thevenin-0.2.1.dist-info/RECORD
