Metadata-Version: 2.4
Name: thevenin
Version: 0.2.1
Summary: Equivalent circuit models in Python.
Author: Corey R. Randall
Author-email: corey.randall@nrel.gov
Maintainer: Corey R. Randall
Maintainer-email: corey.randall@nrel.gov
License-Expression: BSD-3-Clause
Project-URL: Homepage, https://github.com/NREL/thevenin
Project-URL: Documentation, https://thevenin.readthedocs.io
Project-URL: Repository, https://github.com/NREL/thevenin
Project-URL: Issues, https://github.com/NREL/thevenin/issues
Keywords: ECM,equivalent,circuit,model,battery
Classifier: Development Status :: 5 - Production/Stable
Classifier: Intended Audience :: Science/Research
Classifier: Programming Language :: Python :: 3
Classifier: Programming Language :: Python :: 3.9
Classifier: Programming Language :: Python :: 3.10
Classifier: Programming Language :: Python :: 3.11
Classifier: Programming Language :: Python :: 3.12
Classifier: Programming Language :: Python :: 3.13
Requires-Python: <3.14,>=3.9
License-File: LICENSE
Requires-Dist: numpy
Requires-Dist: scipy
Requires-Dist: matplotlib
Requires-Dist: ruamel.yaml
Requires-Dist: scikit-sundae>=1.0.1
Provides-Extra: docs
Requires-Dist: sphinx; extra == "docs"
Requires-Dist: myst-nb; extra == "docs"
Requires-Dist: sphinx-design; extra == "docs"
Requires-Dist: sphinx-autoapi; extra == "docs"
Requires-Dist: sphinx-favicon; extra == "docs"
Requires-Dist: sphinx-copybutton; extra == "docs"
Requires-Dist: pydata-sphinx-theme; extra == "docs"
Provides-Extra: tests
Requires-Dist: pytest; extra == "tests"
Requires-Dist: pytest-cov; extra == "tests"
Requires-Dist: pytest-xdist; extra == "tests"
Provides-Extra: dev
Requires-Dist: nox; extra == "dev"
Requires-Dist: flake8; extra == "dev"
Requires-Dist: autopep8; extra == "dev"
Requires-Dist: codespell; extra == "dev"
Requires-Dist: genbadge[all]; extra == "dev"
Requires-Dist: thevenin[docs,tests]; extra == "dev"
Dynamic: license-file
